foo_devup_hungbd/__init__.py
foo_devup_hungbd/hello.py
foo_devup_hungbd-0.0.1.dist-info/LICENSE
foo_devup_hungbd-0.0.1.dist-info/METADATA
foo_devup_hungbd-0.0.1.dist-info/WHEEL
foo_devup_hungbd-0.0.1.dist-info/top_level.txt
foo_devup_hungbd-0.0.1.dist-info/RECORD
